{
   "JO": [
      "AP-JO-30-W06",
      "AP-JO-30-W04",
      "AP-JO-30-W23",
      "AP-JO-30-W39",
      "AP-JO-30-W01",
      "AP-JO-60-W45",
      "AP-JO-30-W02",
      "AP-JO-10-W17",
      "AP-JO-10-W18",
      "AP-JO-10-W61",
      "AP-JO-10-W60",
      "AP-JO-30-W38",
      "AP-JO-30-W20",
      "AP-JO-30-W03",
      "AP-JO-30-W43",
      "AP-JO-10-W37",
      "AP-JO-30-W08",
      "AP-JO-10-W36",
      "AP-JO-60-W46",
      "AP-JO-10-W19",
      "AP-JO-60-W48",
      "AP-JO-50-W63",
      "AP-JO-30-W42",
      "AP-JO-60-W47",
      "AP-JO-60-W64",
      "AP-JO-30-W41",
      "AP-JO-30-W07",
      "AP-JO-10-W35",
      "AP-JO-30-W40",
      "AP-JO-60-W44",
      "AP-JO-60-W09",
      "AP-JO-60-W12",
      "AP-JO-10-W59",
      "AP-JO-10-W58",
      "AP-JO-60-W27",
      "AP-JO-60-W28",
      "AP-JO-50-W30",
      "AP-JO-30-W05",
      "AP-JO-10-W34",
      "AP-JO-60-W50",
      "AP-JO-60-W51",
      "AP-JO-50-W52",
      "AP-JO-30-W22",
      "AP-JO-30-W25",
      "AP-JO-10-W13",
      "AP-JO-30-W26",
      "AP-JO-10-W14",
      "AP-JO-50-W53",
      "AP-JO-30-W24",
      "AP-JO-60-W29",
      "AP-JO-50-W62",
      "AP-JO-50-W54",
      "AP-JO-10-W56",
      "AP-JO-10-W33",
      "AP-JO-60-W11",
      "AP-JO-50-W31",
      "AP-JO-30-W21",
      "AP-JO-10-W32",
      "AP-JO-10-W55",
      "AP-JO-10-W15",
      "AP-JO-10-W57",
      "AP-JO-10-W16",
      "AP-JO-60-W10"
   ],
   "RES": [
      "AP-RES-P1-W10",
      "AP-RES-P2-W14",
      "AP-RES-P3-W24",
      "AP-RES-P0-W05",
      "AP-RES-P2-W11",
      "AP-RES-P2-W12",
      "AP-RES-P2-W15",
      "AP-RES-P0-W04",
      "AP-RES-P3-W23",
      "AP-RES-P3-W20",
      "AP-RES-P2-W16",
      "AP-RES-P1-W07",
      "AP-RES-P1-W09",
      "AP-RES-P2-W17",
      "AP-RES-P0-W02",
      "AP-RES-P1-W06",
      "AP-RES-P3-W21",
      "AP-RES-P0-W01"
   ],
   "MA": [
      "AP-MA-A-W24",
      "AP-MA-A1-W07",
      "AP-MA-A-W23",
      "AP-MA-A1-W27",
      "AP-MA-B-W09",
      "AP-MA-A-W03",
      "AP-MA-A1-W26",
      "AP-MA-A-W42",
      "AP-MA-A-W40",
      "AP-MA-A1-W08",
      "AP-MA-B-W10",
      "AP-MA-A-W22",
      "AP-MA-A1-W29",
      "AP-MA-A-W04",
      "AP-MA-A1-W05",
      "AP-MA-A-W43",
      "AP-MA-A1-W28",
      "AP-MA-B-W45",
      "AP-MA-C-W19",
      "AP-MA-B-W11",
      "AP-MA-B-W13",
      "AP-MA-A-W02",
      "AP-MA-C-W41",
      "AP-MA-A1-W25",
      "AP-MA-C-W34",
      "AP-MA-A1-W06",
      "AP-MA-C-W14",
      "AP-MA-C-W35",
      "AP-MA-C-W36",
      "AP-MA-B-W12",
      "AP-MA-B-W31",
      "AP-MA-B-W30",
      "AP-MA-C-W37",
      "AP-MA-A-W01",
      "AP-MA-A-W39",
      "AP-MA-C-W16",
      "AP-MA-B-W32",
      "AP-MA-A-W21",
      "AP-MA-C-W15",
      "AP-MA-B-W33",
      "AP-MA-C-W18",
      "AP-MA-C-W17",
      "AP-MA-C-W38"
   ],
   "AT": [
      "AP-AT-03-W20",
      "AP-AT-06-W30",
      "AP-AT-06-W39",
      "AP-AT-06-W31",
      "AP-AT-03-W23",
      "AP-AT-02-W01",
      "AP-AT-03-W24",
      "AP-AT-06-W32",
      "AP-AT-11-W38",
      "AP-AT-11-W19",
      "AP-AT-02-W15",
      "AP-AT-06-W27",
      "AP-AT-06-W28",
      "AP-AT-06-W29",
      "AP-AT-02-W11",
      "AP-AT-03-W21",
      "AP-AT-02-W07",
      "AP-AT-02-W18",
      "AP-AT-02-W16",
      "AP-AT-11-W41",
      "AP-AT-06-W34",
      "AP-AT-03-W36-37",
      "AP-AT-02-W17",
      "AP-AT-02-W14",
      "AP-AT-03-W22",
      "AP-AT-06-W33",
      "AP-AT-06-W09",
      "AP-AT-06-W08",
      "AP-AT-03-W26",
      "AP-AT-02-W10",
      "AP-AT-03-W25",
      "AP-AT-03-W35",
      "AP-AT-02-W06",
      "AP-AT-02-W02",
      "AP-AT-02-W04",
      "AP-PF-PF-W01"
   ],
   "SL": [
      "AP-SL-08-W29",
      "AP-SL-05-W17",
      "AP-SL-02-W13",
      "AP-SL-BIB-W15",
      "AP-SL-05-W10",
      "AP-SL-04-W03",
      "AP-SL-02-W22",
      "AP-SL-02-W27",
      "AP-SL-01-W06",
      "AP-SL-02-W23",
      "AP-SL-02-W28",
      "AP-SL-BIB-W14",
      "AP-SL-02-W21",
      "AP-SL-02-W19",
      "AP-SL-05-W09",
      "AP-SL-05-W16",
      "AP-SL-01-W05",
      "AP-SL-05-W11",
      "AP-SL-05-W18",
      "AP-SL-02-W26",
      "AP-SL-04-W04",
      "AP-SL-05-W08",
      "AP-SL-02-W20",
      "AP-SL-02-W12",
      "AP-SL-04-W02",
      "AP-SL-02-W24",
      "AP-SL-02-W25",
      "AP-SL-04-W01"
   ],
   "SCT": [
      "AP-SCT-SOT-W12",
      "AP-SCT-PB-W04nou",
      "AP-SCT-SOT-W25",
      "AP-SCT-SOT-W23",
      "AP-SCT-SOT-W24",
      "AP-SCT-SOT-W09",
      "AP-SCT-SOT-W11",
      "AP-SCT-SOT-W03",
      "AP-SCT-PB-W06",
      "AP-SCT-SOT-W22",
      "AP-SCT-SOT-W26",
      "AP-SCT-PB-W05",
      "AP-SCT-SOT-W10",
      "AP-SCT-PB-W16",
      "AP-SCT-SOT-W02",
      "AP-SCT-PB-W13",
      "AP-SCT-SOT-W27",
      "AP-SCT-PB-W08",
      "AP-SCT-PB-W17",
      "AP-SCT-PB-W21",
      "AP-SCT-PB-W20",
      "AP-SCT-SOT-W01",
      "AP-SCT-PB-W19",
      "AP-SCT-PB-W14",
      "AP-SCT-PB-W18",
      "AP-SCT-PB-W15",
      "AP-SCT-PB-W07"
   ],
   "MO": [
      "AP-MO-Q1-W41",
      "AP-MO-DB-W45",
      "AP-MO-A1-W28",
      "AP-MO-CB-W03",
      "AP-MO-DB-W47",
      "AP-MO-CB-W04",
      "AP-MO-DB-W22",
      "AP-MO-A1-W39",
      "AP-MO-E3-W49",
      "AP-MO-Q1-W29",
      "AP-MO-CB-W05",
      "AP-MO-DB-W51",
      "AP-MO-DB-W37",
      "AP-MO-DB-W16",
      "AP-MO-A1-W40",
      "AP-MO-DB-W36",
      "AP-MO-DB-W19",
      "AP-MO-E3-W50",
      "AP-MO-DB-W46",
      "AP-MO-A1-W27",
      "AP-MO-E3-W48",
      "AP-MO-DB-W35",
      "AP-MO-DB-W24",
      "AP-MO-Q1-W06",
      "AP-MO-Q1-W42",
      "AP-MO-CB-W09",
      "AP-MO-CB-W02",
      "AP-MO-CB-W01",
      "AP-MO-A1-W25",
      "AP-MO-DB-W23",
      "AP-MO-Q1-W07",
      "AP-MO-BM-W11",
      "AP-MO-Q1-W43",
      "AP-MO-DB-W21",
      "AP-MO-Q1-W08",
      "AP-MO-DB-W15",
      "AP-MO-BM-W31",
      "AP-MO-A1-W38",
      "AP-MO-BM-W32",
      "AP-MO-BM-W12",
      "AP-MO-BM-W13",
      "AP-MO-BM-W14",
      "AP-MO-DB-W20",
      "AP-MO-DB-W18",
      "AP-MO-BM-W10",
      "AP-MO-Q1-W30",
      "AP-MO-DB-W17",
      "AP-MO-Q1-W44",
      "AP-MO-A1-W26",
      "AP-MO-DB-W34",
      "AP-MO-DB-W33",
      "AP-MO-DB-W52"
   ],
   "CTI": [
      "AP-CTI-01-W04",
      "AP-CTI-01-W01",
      "AP-CTI-01-W05",
      "AP-CTI-01-W02",
      "AP-CTI-01-W06",
      "AP-CTI-01-W07",
      "AP-CTI-01-W09",
      "AP-CTI-01-W08",
      "AP-CTI-01-W03"
   ],
   "RL": [
      "AP-RL-J1-W35",
      "AP-RL-PPAL-W21",
      "AP-RL-L3-W41",
      "AP-RL-L3-W28",
      "AP-RL-PPAL-W36",
      "AP-RL-PPAL-W07",
      "AP-RL-J1-W16",
      "AP-RL-J1-W34",
      "AP-RL-L3-W42",
      "AP-RL-L3-W40",
      "AP-RL-L3-W25",
      "AP-RL-J1-W12",
      "AP-RL-L3-W09",
      "AP-RL-J1-W11",
      "AP-RL-J1-W18",
      "AP-RL-L3-W37",
      "AP-RL-L3-W38",
      "AP-RL-L3-W39",
      "AP-RL-L3-W23",
      "AP-RL-PPAL-W26",
      "AP-RL-L3-W29",
      "AP-RL-PPAL-W01",
      "AP-RL-J1-W19",
      "AP-RL-PPAL-W27",
      "AP-RL-J1-W17",
      "AP-RL-PPAL-W08",
      "AP-RL-J1-W20",
      "AP-RL-PPAL-W32",
      "AP-RL-L3-W15",
      "AP-RL-L3-W04",
      "AP-RL-PPAL-W30",
      "AP-RL-L3-W24",
      "AP-RL-L3-W05",
      "AP-RL-L3-W33",
      "AP-RL-L3-W03",
      "AP-RL-L3-W06",
      "AP-RL-L3-W10",
      "AP-RL-PPAL-W31",
      "AP-RL-PPAL-W13",
      "AP-RL-PPAL-W14",
      "AP-RL-L3-W22",
      "AP-RL-L3-W02"
   ],
   "GC": [
      "AP-GC-H3-W21",
      "AP-GC-UNIO-W36",
      "AP-GC-G2-W16",
      "AP-GC-G2-W18",
      "AP-GC-P4-W27",
      "AP-GC-P4-W24",
      "AP-GC-H3-W29",
      "AP-GC-UNIO-W35",
      "AP-GC-M5-W05",
      "AP-GC-P4-W23",
      "AP-GC-M5-W06",
      "AP-GC-M5-W12",
      "AP-GC-F1-W04",
      "AP-GC-M5-W11",
      "AP-GC-M5-W31",
      "AP-GC-M5-W33",
      "AP-GC-G2-W32",
      "AP-GC-G2-W17",
      "AP-GC-P4-W25",
      "AP-GC-H3-W22",
      "AP-GC-G2-W08",
      "AP-GC-G2-W10",
      "AP-GC-H3-W20",
      "AP-GC-G2-W19",
      "AP-GC-G2-W13",
      "AP-GC-G2-W09",
      "AP-GC-G2-W07nou",
      "AP-GC-G2-W02",
      "AP-GC-G2-W14",
      "AP-GC-G2-W03",
      "AP-GC-UNIO-W37",
      "AP-GC-P4-W28",
      "AP-GC-P4-W26",
      "AP-GC-UNIO-W34",
      "AP-GC-G2-W01"
   ],
   "IE": [
      "AP-IE-IE-W03",
      "AP-IE-IE-W02",
      "AP-IE-IE-W01",
      "AP-IE-IE-W06",
      "AP-IE-IE-W07",
      "AP-IE-IE-W04",
      "AP-IE-IE-W05"
   ],
   "ITD": [
      "AP-ITD-PB-W07",
      "AP-ITD-PB-W10",
      "AP-ITD-PB-W15",
      "AP-ITD-PB-W13",
      "AP-ITD-PB-W04",
      "AP-ITD-PB-W09",
      "AP-ITD-PB-W11",
      "AP-ITD-PB-W02",
      "AP-ITD-PB-W01",
      "AP-ITD-PB-W12",
      "AP-ITD-PB-W08",
      "AP-ITD-PB-W06",
      "AP-ITD-PB-W03",
      "AP-ITD-PB-W05",
      "AP-ITD-PB-W14",
      "AP-ITD-PB-W16"
   ],
   "CEP": [
      "AP-CEP-02-W01",
      "AP-CEP-02-W10",
      "AP-CEP-02-W02",
      "AP-CEP-02-W04",
      "AP-CEP-02-W07",
      "AP-CEP-HIV-W30",
      "AP-CEP-02-W03",
      "AP-CEP-02-W06",
      "AP-CEP-02-W11",
      "AP-CEP-02-W08",
      "AP-CEP-02-W05",
      "AP-CEP-02-W13",
      "AP-CEP-02-W12",
      "AP-CEP-02-W09"
   ],
   "CJ": [
      "AP-CJ-CJ-W01",
      "AP-CJ-PB-W10",
      "AP-CJ-CJ-W05",
      "AP-CJ-CJ-W03",
      "AP-CJ-CJ-W06",
      "AP-CJ-CJ-W04",
      "AP-CJ-CJ-W08"
   ],
   "CL": [
      "AP-CL-CL-W01"
   ],
   "PF": [

   ],
   "SE": [
      "AP-SE-02-W03",
      "AP-SE-02-W05",
      "AP-SE-02-W02",
      "AP-SE-02-W06",
      "AP-SE-02-W01",
      "AP-SE-03-W07",
      "AP-SE-BIB-W09",
      "AP-SE-03-W08"
   ],
   "EIV": [
      "AP-EIV-R2-W03",
      "AP-EIV-R2-W05",
      "AP-EIV-R2-W04",
      "AP-EIV-R2-W09",
      "AP-EIV-R2-W14",
      "AP-EIV-R1-W16",
      "AP-EIV-R2-W18",
      "AP-EIV-R1-W20",
      "AP-EIV-R2-W10",
      "AP-EIV-R2-W17",
      "AP-EIV-R1-W11"
   ],
   "MEN": [
      "AP-MEN-02-W04",
      "AP-MEN-02-W03",
      "AP-MEN-02-W11",
      "AP-MEN-02-W10",
      "AP-MEN-01-W05",
      "AP-MEN-01-W13",
      "AP-MEN-01-W14",
      "AP-MEN-01-W06"
   ]
}